color_transfer/__init__.py
color_transfer/numpy.py
color_transfer/pytorch.py
color_transfer/utils.py
color_transfer_py-0.0.5.dist-info/LICENSE.txt
color_transfer_py-0.0.5.dist-info/METADATA
color_transfer_py-0.0.5.dist-info/WHEEL
color_transfer_py-0.0.5.dist-info/top_level.txt
color_transfer_py-0.0.5.dist-info/RECORD
