Metadata-Version: 2.1
Name: color_transfer_py
Version: 0.0.5
Summary: Color transfer between images
Home-page: https://github.com/ptran1203/color_transfer
Author: Phat Tran
Author-email: phatth1203@gmail.com
Project-URL: Bug Tracker, https://github.com/ptran1203/color_transfer/issues
Classifier: Programming Language :: Python :: 3
Classifier: License :: OSI Approved :: MIT License
Classifier: Operating System :: OS Independent
License-File: LICENSE.txt
Requires-Dist: opencv-python >=4.7.0.72
Requires-Dist: torch >=1.13.0
